sigma/backends/predictiq/__init__.py
sigma/backends/predictiq/predictiq.py
sigma/pipelines/predictiq/__init__.py
sigma/pipelines/predictiq/predictiq.py
pysigma_backend_predictiq-0.1.1.dist-info/entry_points.txt
pysigma_backend_predictiq-0.1.1.dist-info/LICENSE
pysigma_backend_predictiq-0.1.1.dist-info/METADATA
pysigma_backend_predictiq-0.1.1.dist-info/WHEEL
pysigma_backend_predictiq-0.1.1.dist-info/RECORD
