Metadata-Version: 2.3
Name: pySigma-backend-predictiq
Version: 0.1.1
Summary: pySigma predict-iq backend
License: MIT
Author: cyte
Author-email: cyte@cyte.co
Requires-Python: >=3.9,<4.0
Classifier: License :: OSI Approved :: MIT License
Classifier: Programming Language :: Python :: 3
Classifier: Programming Language :: Python :: 3.9
Classifier: Programming Language :: Python :: 3.10
Classifier: Programming Language :: Python :: 3.11
Classifier: Programming Language :: Python :: 3.12
Classifier: Programming Language :: Python :: 3.13
Requires-Dist: pysigma (>=0.11.22,<0.12.0)
Requires-Dist: sigma-cli (>=1.0.6,<2.0.0)
Project-URL: Repository, https://github.com/SigmaHQ/pySigma-backend-predictiq
